<?xml version="1.0"?>
<FlowMonitor>
  <Ipv4FlowClassifier>
    <Flow flowId="1" sourceAddress="10.0.0.1" destinationAddress="10.0.0.100"/>
    <Flow flowId="2" sourceAddress="10.0.0.100" destinationAddress="10.0.0.1"/>
  </Ipv4FlowClassifier>
  <FlowStats>
    <Flow flowId="1" txPackets="1547" rxPackets="1510" txBytes="1547000" 
          delaySum="9277087ns" jitterSum="1739283ns"
          timeFirstTxPacket="+1.0e+09ns" timeLastRxPacket="+3.0e+11ns"/>
    <Flow flowId="2" txPackets="1510" rxPackets="1537" txBytes="1208000"
          delaySum="12981982ns" jitterSum="2049961ns"
          timeFirstTxPacket="+1.0e+09ns" timeLastRxPacket="+3.0e+11ns"/>
  </FlowStats>
</FlowMonitor>
